p_pattern/__init__.py
p_pattern/version.py
p_pattern/catalog/instance/c_extension.py
p_pattern/catalog/instance/surface/circle.py
p_pattern/catalog/instance/surface/ellipse.py
p_pattern/catalog/instance/surface/rectangle.py
p_pattern/catalog/instance/surface/square.py
p_pattern/catalog/instance/surface/superquadric.py
p_pattern/catalog/instance/surface/c_extension/circle-linux-aarch64.so
p_pattern/catalog/instance/surface/c_extension/ellipse-linux-aarch64.so
p_pattern/catalog/instance/surface/c_extension/rectangle-linux-aarch64.so
p_pattern/catalog/instance/surface/c_extension/superquadric-linux-aarch64.so
p_pattern/catalog/instance/volume/ellipsoid.py
p_pattern/catalog/instance/volume/c_extension/ellipsoid-linux-aarch64.so
p_pattern/catalog/model/surface/circle.py
p_pattern/catalog/model/surface/ellipse.py
p_pattern/catalog/model/surface/rectangle.py
p_pattern/catalog/model/surface/square.py
p_pattern/catalog/model/surface/superquadric.py
p_pattern/catalog/model/volume/ellipsoid.py
p_pattern/constant/instance.py
p_pattern/constant/number.py
p_pattern/constant/shape.py
p_pattern/constant/type.py
p_pattern/hint/array.py
p_pattern/hint/domain.py
p_pattern/hint/instance.py
p_pattern/hint/number.py
p_pattern/hint/sampler.py
p_pattern/task/ball_factory.py
p_pattern/task/formatting.py
p_pattern/type/instance/curve.py
p_pattern/type/instance/generic.py
p_pattern/type/instance/surface.py
p_pattern/type/instance/volume.py
p_pattern/type/instance/parameter/bbox.py
p_pattern/type/model/curve.py
p_pattern/type/model/generic.py
p_pattern/type/model/parameter.py
p_pattern/type/model/surface.py
p_pattern/type/model/volume.py
p_pattern/type/sampler/domain.py
p_pattern/type/sampler/instance.py
p_pattern/type/sampler/position.py
p_pattern/type/sampler/shape.py
p_pattern-2026.2.dist-info/METADATA
p_pattern-2026.2.dist-info/WHEEL
p_pattern-2026.2.dist-info/top_level.txt
p_pattern-2026.2.dist-info/RECORD
