Metadata-Version: 2.4
Name: p-pattern
Version: 2026.2
Summary: Parametric patterns/shapes definition and sampling
Home-page: https://src.koda.cnrs.fr/eric.debreuve/p-pattern/
Author: Eric Debreuve
Author-email: eric.debreuve@cnrs.fr
License: CeCILL-2.1
Project-URL: Documentation, https://src.koda.cnrs.fr/eric.debreuve/p-pattern/-/wikis/home
Project-URL: Source, https://src.koda.cnrs.fr/eric.debreuve/p-pattern/
Keywords: parameter,parametric,pattern,shape,sampler,sampling
Classifier: Topic :: Scientific/Engineering :: Image Recognition
Classifier: Intended Audience :: Science/Research
Classifier: License :: OSI Approved :: CEA CNRS Inria Logiciel Libre License, version 2.1 (CeCILL-2.1)
Classifier: Programming Language :: Python :: 3
Classifier: Programming Language :: C
Classifier: Development Status :: 4 - Beta
Requires-Python: >=3.13
Requires-Dist: logger_36
Requires-Dist: numpy
Requires-Dist: scikit-image
Requires-Dist: scipy
Dynamic: author
Dynamic: author-email
Dynamic: classifier
Dynamic: description
Dynamic: description-content-type
Dynamic: home-page
Dynamic: keywords
Dynamic: license
Dynamic: project-url
Dynamic: requires-dist
Dynamic: requires-python
Dynamic: summary
